Metadata-Version: 2.4
Name: suite2p
Version: 0.14.6
Summary: Pipeline for calcium imaging
Home-page: https://github.com/MouseLand/suite2p
Author: Marius Pachitariu and Carsen Stringer
Author-email: marius10p@gmail.com
Classifier: Programming Language :: Python :: 3
Classifier: License :: OSI Approved :: GNU General Public License v3 (GPLv3)
Classifier: Operating System :: OS Independent
License-File: LICENSE
Requires-Dist: importlib-metadata
Requires-Dist: natsort
Requires-Dist: rastermap>=0.9.0
Requires-Dist: tifffile
Requires-Dist: torch>=1.13.1
Requires-Dist: numpy>=1.24.3
Requires-Dist: numba>=0.57.0
Requires-Dist: matplotlib
Requires-Dist: scipy>=1.9.0
Requires-Dist: scikit-learn
Requires-Dist: cellpose>=4.0.1
Requires-Dist: scanimage-tiff-reader>=1.4.1
Provides-Extra: docs
Requires-Dist: sphinx>=3.0; extra == "docs"
Requires-Dist: sphinxcontrib-apidoc; extra == "docs"
Requires-Dist: sphinx_rtd_theme; extra == "docs"
Requires-Dist: sphinx-prompt; extra == "docs"
Requires-Dist: sphinx-autodoc-typehints; extra == "docs"
Provides-Extra: gui
Requires-Dist: qtpy; extra == "gui"
Requires-Dist: pyqt6; extra == "gui"
Requires-Dist: pyqt6.sip; extra == "gui"
Requires-Dist: pyqtgraph; extra == "gui"
Provides-Extra: nwb
Requires-Dist: pynwb>=2.3.2; extra == "nwb"
Provides-Extra: io
Requires-Dist: paramiko; extra == "io"
Requires-Dist: nd2; extra == "io"
Requires-Dist: sbxreader; extra == "io"
Requires-Dist: h5py; extra == "io"
Requires-Dist: opencv-python-headless; extra == "io"
Requires-Dist: xmltodict; extra == "io"
Requires-Dist: dcimg; extra == "io"
Provides-Extra: tests
Requires-Dist: pytest; extra == "tests"
Requires-Dist: tenacity; extra == "tests"
Requires-Dist: tqdm; extra == "tests"
Requires-Dist: pynwb>=2.3.2; extra == "tests"
Requires-Dist: pytest-qt>3.3.0; extra == "tests"
Provides-Extra: all
Requires-Dist: qtpy; extra == "all"
Requires-Dist: pyqt6; extra == "all"
Requires-Dist: pyqt6.sip; extra == "all"
Requires-Dist: pyqtgraph; extra == "all"
Requires-Dist: pynwb>=2.3.2; extra == "all"
Requires-Dist: pytest; extra == "all"
Requires-Dist: tenacity; extra == "all"
Requires-Dist: tqdm; extra == "all"
Requires-Dist: pynwb>=2.3.2; extra == "all"
Requires-Dist: pytest-qt>3.3.0; extra == "all"
Requires-Dist: paramiko; extra == "all"
Requires-Dist: nd2; extra == "all"
Requires-Dist: sbxreader; extra == "all"
Requires-Dist: h5py; extra == "all"
Requires-Dist: opencv-python-headless; extra == "all"
Requires-Dist: xmltodict; extra == "all"
Requires-Dist: dcimg; extra == "all"
Dynamic: author
Dynamic: author-email
Dynamic: classifier
Dynamic: description
Dynamic: description-content-type
Dynamic: home-page
Dynamic: license-file
Dynamic: provides-extra
Dynamic: requires-dist
Dynamic: summary
